{"is_modern": "Y", "has_elevator": "Y", "is_flat": "Y", "location": null, "notes": "Spacious well-maintained apartment with modern finishes including recessed ceiling lighting, split AC units, and updated bathroom with bathtub and glass partition. Good natural light from large windows with floor-to-ceiling glass in bedroom. For baby safety, the glass coffee table corners and open shelving may need childproofing; windows appear to have secure railings. Overall clean and move-in ready condition."}
