{"is_modern": "Y", "has_elevator": "?", "is_flat": "Y", "location": null, "notes": "High-end luxury apartment with contemporary minimalist design, marble-clad bathroom with soaking tub and smart toilet, recessed lighting, and quality furniture. The glass partition bedroom and open floor plan are stylish but present baby safety concerns with sharp furniture corners and hard marble floors throughout. Excellent cleanliness and natural light through multiple windows; includes Ariston washing machine."}
